{
  "Fuel Scoops": {
    "30": {
      "group": "fs",
      "name": "Fuel Scoop",
      "class": 3,
      "rating": "D",
      "cost": 14109,
      "power": 0.27,
      "rate": 100
    },
    "31": {
      "group": "fs",
      "name": "Fuel Scoop",
      "class": 3,
      "rating": "E",
      "cost": 3386,
      "power": 0.2,
      "rate": 75
    },
    "32": {
      "group": "fs",
      "name": "Fuel Scoop",
      "class": 4,
      "rating": "A",
      "cost": 2862364,
      "power": 0.57,
      "rate": 342
    },
    "33": {
      "group": "fs",
      "name": "Fuel Scoop",
      "class": 4,
      "rating": "B",
      "cost": 715591,
      "power": 0.49,
      "rate": 294
    },
    "34": {
      "group": "fs",
      "name": "Fuel Scoop",
      "class": 4,
      "rating": "C",
      "cost": 178898,
      "power": 0.41,
      "rate": 245
    },
    "35": {
      "group": "fs",
      "name": "Fuel Scoop",
      "class": 4,
      "rating": "D",
      "cost": 44724,
      "power": 0.33,
      "rate": 196
    },
    "36": {
      "group": "fs",
      "name": "Fuel Scoop",
      "class": 4,
      "rating": "E",
      "cost": 10734,
      "power": 0.25,
      "rate": 147
    },
    "37": {
      "group": "fs",
      "name": "Fuel Scoop",
      "class": 5,
      "rating": "A",
      "cost": 9073694,
      "power": 0.7,
      "rate": 577
    },
    "38": {
      "group": "fs",
      "name": "Fuel Scoop",
      "class": 5,
      "rating": "B",
      "cost": 2268424,
      "power": 0.6,
      "rate": 494
    },
    "39": {
      "group": "fs",
      "name": "Fuel Scoop",
      "class": 5,
      "rating": "C",
      "cost": 567106,
      "power": 0.5,
      "rate": 412
    },
    "2j": {
      "group": "fs",
      "name": "Fuel Scoop",
      "class": 1,
      "rating": "A",
      "cost": 82270,
      "power": 0.32,
      "rate": 42
    },
    "2k": {
      "group": "fs",
      "name": "Fuel Scoop",
      "class": 1,
      "rating": "B",
      "cost": 20568,
      "power": 0.28,
      "rate": 36
    },
    "2l": {
      "group": "fs",
      "name": "Fuel Scoop",
      "class": 1,
      "rating": "C",
      "cost": 5142,
      "power": 0.23,
      "rate": 30
    },
    "2m": {
      "group": "fs",
      "name": "Fuel Scoop",
      "class": 1,
      "rating": "D",
      "cost": 1285,
      "power": 0.18,
      "rate": 24
    },
    "2n": {
      "group": "fs",
      "name": "Fuel Scoop",
      "class": 1,
      "rating": "E",
      "cost": 309,
      "power": 0.14,
      "rate": 18
    },
    "2o": {
      "group": "fs",
      "name": "Fuel Scoop",
      "class": 2,
      "rating": "A",
      "cost": 284844,
      "power": 0.39,
      "rate": 75
    },
    "2p": {
      "group": "fs",
      "name": "Fuel Scoop",
      "class": 2,
      "rating": "B",
      "cost": 71211,
      "power": 0.34,
      "rate": 65
    },
    "2q": {
      "group": "fs",
      "name": "Fuel Scoop",
      "class": 2,
      "rating": "C",
      "cost": 17803,
      "power": 0.28,
      "rate": 54
    },
    "2r": {
      "group": "fs",
      "name": "Fuel Scoop",
      "class": 2,
      "rating": "D",
      "cost": 4451,
      "power": 0.22,
      "rate": 43
    },
    "2s": {
      "group": "fs",
      "name": "Fuel Scoop",
      "class": 2,
      "rating": "E",
      "cost": 1068,
      "power": 0.17,
      "rate": 32
    },
    "2t": {
      "group": "fs",
      "name": "Fuel Scoop",
      "class": 3,
      "rating": "A",
      "cost": 902954,
      "power": 0.48,
      "rate": 176
    },
    "2u": {
      "group": "fs",
      "name": "Fuel Scoop",
      "class": 3,
      "rating": "B",
      "cost": 225738,
      "power": 0.41,
      "rate": 151
    },
    "2v": {
      "group": "fs",
      "name": "Fuel Scoop",
      "class": 3,
      "rating": "C",
      "cost": 56435,
      "power": 0.34,
      "rate": 126
    },
    "3a": {
      "group": "fs",
      "name": "Fuel Scoop",
      "class": 5,
      "rating": "D",
      "cost": 141776,
      "power": 0.4,
      "rate": 330
    },
    "3b": {
      "group": "fs",
      "name": "Fuel Scoop",
      "class": 5,
      "rating": "E",
      "cost": 34026,
      "power": 0.3,
      "rate": 247
    },
    "3c": {
      "group": "fs",
      "name": "Fuel Scoop",
      "class": 6,
      "rating": "A",
      "cost": 28763610,
      "power": 0.83,
      "rate": 878
    },
    "3d": {
      "group": "fs",
      "name": "Fuel Scoop",
      "class": 6,
      "rating": "B",
      "cost": 7190903,
      "power": 0.71,
      "rate": 752
    },
    "3e": {
      "group": "fs",
      "name": "Fuel Scoop",
      "class": 6,
      "rating": "C",
      "cost": 1797726,
      "power": 0.59,
      "rate": 627
    },
    "3f": {
      "group": "fs",
      "name": "Fuel Scoop",
      "class": 6,
      "rating": "D",
      "cost": 449431,
      "power": 0.47,
      "rate": 502
    },
    "3g": {
      "group": "fs",
      "name": "Fuel Scoop",
      "class": 6,
      "rating": "E",
      "cost": 107864,
      "power": 0.35,
      "rate": 376
    },
    "3h": {
      "group": "fs",
      "name": "Fuel Scoop",
      "class": 7,
      "rating": "A",
      "cost": 91180644,
      "power": 0.97,
      "rate": 1245
    },
    "3i": {
      "group": "fs",
      "name": "Fuel Scoop",
      "class": 7,
      "rating": "B",
      "cost": 22795161,
      "power": 0.83,
      "rate": 1068
    },
    "3j": {
      "group": "fs",
      "name": "Fuel Scoop",
      "class": 7,
      "rating": "C",
      "cost": 5698790,
      "power": 0.69,
      "rate": 890
    },
    "3k": {
      "group": "fs",
      "name": "Fuel Scoop",
      "class": 7,
      "rating": "D",
      "cost": 1424698,
      "power": 0.55,
      "rate": 712
    },
    "3l": {
      "group": "fs",
      "name": "Fuel Scoop",
      "class": 7,
      "rating": "E",
      "cost": 341927,
      "power": 0.41,
      "rate": 534
    },
    "3m": {
      "group": "fs",
      "name": "Fuel Scoop",
      "class": 8,
      "rating": "A",
      "cost": 289042541,
      "power": 1.12,
      "rate": 1680
    },
    "3n": {
      "group": "fs",
      "name": "Fuel Scoop",
      "class": 8,
      "rating": "B",
      "cost": 72260660,
      "power": 0.96,
      "rate": 1440
    },
    "3o": {
      "group": "fs",
      "name": "Fuel Scoop",
      "class": 8,
      "rating": "C",
      "cost": 18065165,
      "power": 0.8,
      "rate": 1200
    },
    "3p": {
      "group": "fs",
      "name": "Fuel Scoop",
      "class": 8,
      "rating": "D",
      "cost": 4516291,
      "power": 0.64,
      "rate": 960
    },
    "3q": {
      "group": "fs",
      "name": "Fuel Scoop",
      "class": 8,
      "rating": "E",
      "cost": 1083910,
      "power": 0.48,
      "rate": 720
    }
  }
}